arkab/__init__.py
arkab/config.py
arkab/data.py
arkab/debug.py
arkab/delegates.py
arkab/fs.py
arkab/graph.py
arkab/logger.py
arkab/metrics.py
arkab/trainer.py
arkab/utils.py
arkab/wrapper.py
arkab/data/__init__.py
arkab/data/data.py
arkab/lightning/__init__.py
arkab/lightning/config.py
arkab/lightning/training.py
arkab/nlp/__init__.py
arkab/nlp/dataset.py
arkab/nlp/knowledge.py
arkab/nlp/sequence.py
arkab/nlp/utils.py
arkab/nlp/bin/__init__.py
arkab/nlp/bin/kg.py
arkab/sequence/__init__.py
arkab/sequence/padding.py
arkab/tensorflow/__init__.py
arkab/tensorflow/dataloader.py
arkab/tensorflow/headers.py
arkab/tensorflow/metrics.py
arkab/tensorflow/wrapper.py
arkab/torch/__init__.py
arkab/torch/dataloader.py
arkab/torch/layers.py
arkab/torch/nn.py
arkab/torch/tensor.py
arkab/torch/utils.py
arkab/torch/wrapper.py
arkab-0.3.141.data/scripts/arkab
arkab-0.3.141.dist-info/LICENSE
arkab-0.3.141.dist-info/METADATA
arkab-0.3.141.dist-info/WHEEL
arkab-0.3.141.dist-info/top_level.txt
arkab-0.3.141.dist-info/RECORD
