Metadata-Version: 2.1
Name: arkab
Version: 0.3.141
Summary: DeepLearning Toolkit for myself
Home-page: UNKNOWN
Author: gawainx
Author-email: liangyi@bupt.edu.cn
License: UNKNOWN
Platform: UNKNOWN
Classifier: Programming Language :: Python :: 3.8
Classifier: License :: OSI Approved :: GNU General Public License v3 (GPLv3)
Classifier: Operating System :: OS Independent
Requires-Dist: numpy
Requires-Dist: torch
Requires-Dist: networkx
Requires-Dist: toml
Requires-Dist: typer
Requires-Dist: rich
Requires-Dist: seqeval
Requires-Dist: gxCastor
